MotionBotList/Exceptions.py
MotionBotList/Objects.py
MotionBotList/__init__.py
motionbotlist-1.0.3.dist-info/LICENSE
motionbotlist-1.0.3.dist-info/METADATA
motionbotlist-1.0.3.dist-info/WHEEL
motionbotlist-1.0.3.dist-info/top_level.txt
motionbotlist-1.0.3.dist-info/RECORD
