Metadata-Version: 2.1
Name: motionbotlist
Version: 1.0.3
Summary: Motion bot list status api tool
Home-page: UNKNOWN
Author: TechnicPepijn
Author-email: <tech@motiondevelopment.top>
License: UNKNOWN
Keywords: python,discord,disocrd-botlist,discord-bots,bots,botlist,motion,motiondev,motiondevelopment,motionbotlist
Platform: UNKNOWN
Classifier: Development Status :: 5 - Production/Stable
Classifier: Intended Audience :: Developers
Classifier: Programming Language :: Python :: 3
Classifier: Operating System :: Unix
Classifier: Operating System :: MacOS :: MacOS X
Classifier: Operating System :: Microsoft :: Windows
Requires-Dist: requests
